hypothesis_grammar/__init__.py
hypothesis_grammar/generate.py
hypothesis_grammar/grammar.lark
hypothesis_grammar/parser.py
hypothesis_grammar/types.py
hypothesis_grammar-0.1.1.dist-info/LICENSE
hypothesis_grammar-0.1.1.dist-info/WHEEL
hypothesis_grammar-0.1.1.dist-info/METADATA
hypothesis_grammar-0.1.1.dist-info/RECORD
